manila_ui/__init__.py
manila_ui/exceptions.py
manila_ui/features.py
manila_ui/api/__init__.py
manila_ui/api/manila.py
manila_ui/conf/manila_policy.yaml
manila_ui/conf/default_policies/manila.yaml
manila_ui/dashboards/__init__.py
manila_ui/dashboards/utils.py
manila_ui/dashboards/admin/__init__.py
manila_ui/dashboards/admin/utils.py
manila_ui/dashboards/admin/defaults/__init__.py
manila_ui/dashboards/admin/defaults/tables.py
manila_ui/dashboards/admin/defaults/tabs.py
manila_ui/dashboards/admin/defaults/workflows.py
manila_ui/dashboards/admin/security_services/__init__.py
manila_ui/dashboards/admin/security_services/panel.py
manila_ui/dashboards/admin/security_services/tables.py
manila_ui/dashboards/admin/security_services/tabs.py
manila_ui/dashboards/admin/security_services/urls.py
manila_ui/dashboards/admin/security_services/views.py
manila_ui/dashboards/admin/security_services/templates/security_services/_detail.html
manila_ui/dashboards/admin/security_services/templates/security_services/detail.html
manila_ui/dashboards/admin/security_services/templates/security_services/index.html
manila_ui/dashboards/admin/share_group_snapshots/__init__.py
manila_ui/dashboards/admin/share_group_snapshots/forms.py
manila_ui/dashboards/admin/share_group_snapshots/panel.py
manila_ui/dashboards/admin/share_group_snapshots/tables.py
manila_ui/dashboards/admin/share_group_snapshots/tabs.py
manila_ui/dashboards/admin/share_group_snapshots/urls.py
manila_ui/dashboards/admin/share_group_snapshots/views.py
manila_ui/dashboards/admin/share_group_snapshots/templates/share_group_snapshots/_detail.html
manila_ui/dashboards/admin/share_group_snapshots/templates/share_group_snapshots/_reset_status.html
manila_ui/dashboards/admin/share_group_snapshots/templates/share_group_snapshots/detail.html
manila_ui/dashboards/admin/share_group_snapshots/templates/share_group_snapshots/index.html
manila_ui/dashboards/admin/share_group_snapshots/templates/share_group_snapshots/reset_status.html
manila_ui-14.0.0.dist-info/AUTHORS
manila_ui-14.0.0.dist-info/LICENSE
manila_ui-14.0.0.dist-info/METADATA
manila_ui-14.0.0.dist-info/WHEEL
manila_ui-14.0.0.dist-info/pbr.json
manila_ui-14.0.0.dist-info/top_level.txt
manila_ui-14.0.0.dist-info/RECORD
