Metadata-Version: 2.1
Name: manila-ui
Version: 14.0.0
Summary: Manila Management Dashboard
Home-page: https://docs.openstack.org/manila-ui/latest/
Author: OpenStack
Author-email: openstack-discuss@lists.openstack.org
Classifier: Environment :: OpenStack
Classifier: Intended Audience :: Information Technology
Classifier: Intended Audience :: System Administrators
Classifier: License :: OSI Approved :: Apache Software License
Classifier: Operating System :: POSIX :: Linux
Classifier: Programming Language :: Python
Classifier: Programming Language :: Python :: Implementation :: CPython
Classifier: Programming Language :: Python :: 3 :: Only
Classifier: Programming Language :: Python :: 3
Classifier: Programming Language :: Python :: 3.10
Classifier: Programming Language :: Python :: 3.11
Classifier: Programming Language :: Python :: 3.12
Requires-Python: >=3.10
License-File: LICENSE
License-File: AUTHORS
Requires-Dist: pbr >=5.5.0
Requires-Dist: django-compressor >=2.0
Requires-Dist: oslo.utils >=4.7.0
Requires-Dist: python-keystoneclient >=4.1.1
Requires-Dist: python-manilaclient >=2.7.0
Requires-Dist: horizon >=18.3.1
